plu/VERSION
plu/__init__.py
plu/balance.py
plu/dataloader.py
plu/soundcheck.py
plu/test.py
plu/tok.py
plu/train.py
plu-0.1.18.dist-info/LICENSE
plu-0.1.18.dist-info/METADATA
plu-0.1.18.dist-info/WHEEL
plu-0.1.18.dist-info/entry_points.txt
plu-0.1.18.dist-info/top_level.txt
plu-0.1.18.dist-info/RECORD
