Metadata-Version: 2.1
Name: plu
Version: 0.1.18
Summary: audio-conditional language models are multi-task recognizers
Home-page: https://github.com/proger/plu
Author: Vol Kyrylov
Author-email: vol@wilab.org.ua
License: Apache License, Version 2.0
Project-URL: Issues, https://github.com/proger/plu/issues
Project-URL: CI, https://github.com/proger/plu/actions
Project-URL: Changelog, https://github.com/proger/plu/releases
Requires-Python: >=3.8
License-File: LICENSE
Requires-Dist: tiktoken
Requires-Dist: openai-whisper
Requires-Dist: soundfile
Requires-Dist: transformers
Requires-Dist: datasets
Requires-Dist: peft
Requires-Dist: accelerate
Requires-Dist: faster-whisper
Requires-Dist: click
